algophon/__init__.py
algophon/ipa.txt
algophon/natclass.py
algophon/seg.py
algophon/seginv.py
algophon/segstr.py
algophon/symbols.py
algophon/data_structures/__init__.py
algophon/data_structures/graph.py
algophon/distance/__init__.py
algophon/distance/edit_distance.py
algophon/ipa/__init__.py
algophon/ipa/convert.py
algophon/models/__init__.py
algophon/models/D2L/__init__.py
algophon/models/D2L/d2l.py
algophon/models/D2L/discrepancy.py
algophon/models/D2L/rule.py
algophon/models/D2L/tier.py
algophon/models/Miaseg/__init__.py
algophon/models/Miaseg/miaseg.py
algophon/models/Miaseg/paradigm.py
algophon/utils/__init__.py
algophon/utils/utils.py
algophon-0.1.6.dist-info/LICENSE
algophon-0.1.6.dist-info/METADATA
algophon-0.1.6.dist-info/WHEEL
algophon-0.1.6.dist-info/top_level.txt
algophon-0.1.6.dist-info/RECORD
